instainfo
