Metadata-Version: 2.1
Name: instainfo
Version: 0.0.4
Summary: Get Profile information of a instagram user
Home-page: http://github.com/haydencordeiro
Author: Hayden Cordeiro
Author-email: cordeirohayden@gmail.com
License: UNKNOWN
Platform: UNKNOWN
Classifier: Programming Language :: Python :: 3
Classifier: License :: OSI Approved :: MIT License
Classifier: Operating System :: OS Independent
